app/__init__.py
app/consts.py
app/database_manager.py
app/main.py
app/utils.py
app/templates/index.html
tests/__init__.py
tests/test_split_text.py
plagiarism_check_app-0.0.18.dist-info/LICENSE
plagiarism_check_app-0.0.18.dist-info/METADATA
plagiarism_check_app-0.0.18.dist-info/WHEEL
plagiarism_check_app-0.0.18.dist-info/entry_points.txt
plagiarism_check_app-0.0.18.dist-info/top_level.txt
plagiarism_check_app-0.0.18.dist-info/RECORD
