Metadata-Version: 2.1
Name: plagiarism_check_app
Version: 0.0.18
Summary: A FastAPI app
Home-page: https://github.com/viraboik/plagiarismcheck.git
Author: Vira Boiko
Author-email: vira.shendrykk@gmail.com
License-File: LICENSE
Requires-Dist: fastapi ==0.115.0
Requires-Dist: uvicorn ==0.31.1
Requires-Dist: nltk ==3.9.1
Requires-Dist: pytest ==8.3.3
Requires-Dist: jinja2 ==3.1.4
